{
  "release": {
    "enable": true,
    "version": "3.2.0LTS",
    "versionDate": "2026-02-02T21:30",
    "releaseLink": "https://github.com/QingFengTechnology/FengAmongUsTool/releases/tag/v3.2.0LTS",
    "autoUpdate": false,
    "donloadUrl": {
      "github": "https://github.com/QingFengTechnology/FengAmongUsTool/releases/download/v3.2.0LTS/FengAmongUsTool.zip",
      "api": null
    }
  },
  "preview": {
    "enable": false
  },
  "beta": {
    "enable": false
  },
  "alpha": {
    "enable": false
  }
}